ee4363/mp2/mipspipe_mp2.v
// Incomplete behavioral model of MIPS pipeline

module mipspipe_mp2 (clock);
  // in_out
  input clock;

  // Instruction opcodes
  parameter LW = 6'b100011, SW = 6'b101011, BEQ = 6'b000100, nop = 32'b00000_100000, ALUop = 6'b0;
  reg [31:0] PC, Regs[0:31], IMemory[0:1023], DMemory[0:1023], // instruction and data memories
             IFIDIR, IDEXA, IDEXB, IDEXIR, EXMEMIR, EXMEMB, // pipeline latches
             EXMEMALUOut, MEMWBValue, MEMWBIR;

  wire [4:0] IDEXrs, IDEXrt, EXMEMrd, MEMWBrd, MEMWBrt, IFIDrt, IFIDrs; // hold register fields
  wire [5:0] EXMEMop, MEMWBop, IDEXop, IFIDop; // hold opcodes
  wire [31:0] Ain, Bin; // ALU inputs

  // declare the bypass signals
  wire bypassAfromMEM, bypassAfromALUinWB, bypassBfromMEM, bypassBfromALUinWB, bypassAfromLWinWB, bypassBfromLWinWB, bypassIDEXAfromWB, bypassIDEXBfromWB, STALL;

   // Define fields of pipeline latches
   assign IDEXrs = IDEXIR[25:21]; // rs field
   assign IDEXrt = IDEXIR[20:16]; // rt field
   assign EXMEMrd = EXMEMIR[15:11]; // rd field
   assign MEMWBrd = MEMWBIR[15:11]; // rd field
   assign MEMWBrt = MEMWBIR[20:16]; // rt field -- for loads
   assign EXMEMop = EXMEMIR[31:26]; // opcode
   assign MEMWBop = MEMWBIR[31:26]; // opcode
   assign IDEXop = IDEXIR[31:26]; // opcode
   assign IFIDrs = IFIDIR[25:21];
   assign IFIDrt = IFIDIR[20:16];
   assign IFIDop = IFIDIR[31:26]; 


  // The bypass to input A from the MEM stage for an ALU operation
  assign bypassAfromMEM = (IDEXrs == EXMEMrd) & (IDEXrs!=0) & (EXMEMop==ALUop);
  // The bypass to input B from the MEM stage for an ALU operation
  assign bypassBfromMEM = 0;
  // The bypass to input A from the WB stage for an ALU operation
  assign bypassAfromALUinWB = 0;
  // The bypass to input B from the WB stage for an ALU operation
  assign bypassBfromALUinWB = 0; 
  // The bypass to input A from the WB stage for an LW operation
  assign bypassAfromLWinWB = (IDEXrs == MEMWBIR[20:16]) & (IDEXrs!=0) & (MEMWBop==LW);
  // The bypass to input B from the WB stage for an LW operation
  assign bypassBfromLWinWB = 0;
  //Stall in case of WB
  assign bypassIDEXAfromWB = ((MEMWBIR != nop) & (IFIDIR != nop) & (IFIDrs == MEMWBrt) & (MEMWBop == LW)) | 
    ((MEMWBop == ALUop) & (MEMWBrd == IFIDrs)); 
  assign bypassIDEXBfromWB = ((MEMWBIR != nop) & (IFIDIR != nop) & (IFIDrt == MEMWBrt) & (MEMWBop == LW)) | 
    ((MEMWBop == ALUop) & (MEMWBrd == IFIDrt)); 
  // The A input to the ALU is bypassed from MEM if there is a bypass there,
  // Otherwise from WB if there is a bypass there, and otherwise comes from the IDEX register
  assign Ain = bypassAfromMEM? EXMEMALUOut : (bypassAfromALUinWB | bypassAfromLWinWB)? MEMWBValue : IDEXA;

  // The B input to the ALU is bypassed from MEM if there is a bypass there,
  // Otherwise from WB if there is a bypass there, and otherwise comes from the IDEX register
  // Ripped off of above just replacing "A" with "B"
  assign Bin = bypassBfromMEM? EXMEMALUOut : (bypassBfromALUinWB | bypassBfromLWinWB)? MEMWBValue : IDEXB;


  reg [5:0] i; // used to initialize latches
  reg [10:0] j,k; // used to initialize memories

  // Make the Big Stall
  assign STALL = (IDEXop == LW) && 
    //All of this is anded with the above (Lisp would be proud)
    (((IFIDop == LW) && (IFIDrs == IDEXrt)) |
    ((IFIDop == ALUop) && ((IFIDrs == IDEXrt) | (IFIDrt == IDEXrt))) |
    ((IFIDop == SW) && ((IFIDrs == IDEXrt) | (IFIDrt == IDEXrt))));
  
  initial begin
    PC = 0;
    IFIDIR = nop; 
    IDEXIR = nop; 
    EXMEMIR = nop; 
    MEMWBIR = nop; // no-ops in pipeline latches
  
    for (i = 0;i<=31;i = i+1) Regs[i] = i; // initialize latches
  
    IMemory[0] = 32'h00412820; // ADD $5, $2, $1
    IMemory[1] = 32'h8ca30004; // LW $3, 4($5)
    IMemory[2] = 32'haca70005; // SW $7, 5($5)
    // Hazard 1: ADD might not have written to $5 before SW reads from $5 (Type 2: Read after Write)
    IMemory[3] = 32'h00602020; // ADD $4, $3, $0
    // Hazard 2: ADD might read $3 before LW writes to $3 (Type 3: Write after read)
    IMemory[4] = 32'h01093020; // ADD $6, $8, $9
    IMemory[5] = 32'hac06000c; // SW $6, $12($0)
    // Hazard 3: ADD and SW are trying to access the same register (Type 1: Write after Write)
    IMemory[6] = 32'h00c05020; // ADD $10, $6, $0
    // Hazard 4: ADD reads from $6 and is written to (twice) immediately beforehand (Type 2: Read after Write)
    IMemory[7] = 32'h8c0b0010; // LW $11, 32($0)
    IMemory[8] = 32'h00000020; // ADD $0, $0, $0
    IMemory[9] = 32'h002b6020; // ADD $12, $1, $11
    // Hazard 5: LW might not have written to $11 before the last ADD reads from $11 (Type 2: Read after Write)
    for (j=10; j<=1023; j=j+1) IMemory[j] = nop;
    
    DMemory[0] = 32'h00000000;
    DMemory[1] = 32'hffffffff;
    DMemory[2] = 32'h00000000;
    DMemory[3] = 32'h00000000;
    DMemory[4] = 32'hfffffffe;
    for (k=5; k<=1023; k=k+1) DMemory[k] = 0;
  end

  always @ (posedge clock) begin
    if (~STALL) begin
	  // FETCH: Fetch instruction & update PC
      IFIDIR <= IMemory[PC>>2];
      PC <= PC + 4;

      // DECODE: Read registers
      if (~bypassIDEXAfromWB) begin
        IDEXA <= Regs[IFIDIR[25:21]]; 
      end 
       else begin
          IDEXA <= MEMWBValue;
      end

      if (~bypassIDEXBfromWB) begin
        IDEXB <= Regs[IFIDIR[20:16]];
      end 
       else begin
        IDEXB <= MEMWBValue;
      end
        IDEXIR <= IFIDIR; 
    end 
     else begin //IF (STALL)
        IDEXIR <= nop;
    end

    // EX: Address calculation or ALU operation
    if ((IDEXop==LW) |(IDEXop==SW)) // address calculation & copy B
       EXMEMALUOut <= Ain +{{16{IDEXIR[15]}}, IDEXIR[15:0]};
    else if (IDEXop==ALUop) begin
       case (IDEXIR[5:0]) // R-type instruction
         32: EXMEMALUOut <= Ain + Bin; // add operation
         default: ; // other R-type operations: subtract, SLT, etc.
       endcase
    end
   
    EXMEMIR <= IDEXIR; 
    EXMEMB <= Bin; // pass along the IR & B register
   
    // MEM
    if (EXMEMop==ALUop) MEMWBValue <= EXMEMALUOut; // pass along ALU result
    else if (EXMEMop == LW) MEMWBValue <= DMemory[EXMEMALUOut>>2];
    else if (EXMEMop == SW) DMemory[EXMEMALUOut>>2] <=EXMEMB; // store
   
    MEMWBIR <= EXMEMIR; // pass along IR
   
    // WB 
    if ((MEMWBop==ALUop) & (MEMWBrd != 0)) // update latches if ALU operation and destination not 0
    Regs[MEMWBrd] <= MEMWBValue; // ALU operation
    else if ((MEMWBop == LW)& (MEMWBrt != 0)) // Update latches if load and destination not 0
    Regs[MEMWBrt] <= MEMWBValue;
  end

endmodule

ee4363/mp2/test_mipspipe_mp2.v
//
// Test bench for the mipspipe
// Boram Lee
//
  
`include "mipspipe_mp2.v"
  
module test_mipspipe;
  
  reg clock;
  reg [3:0] clock_cycle;

// instantiate pipeline module
  mipspipe_mp2 u_mipspipe_mp2(clock);
 
// initialize clock and cycle counter 
  initial begin
    clock = 0;
    clock_cycle=4'h0;
    #160  $finish;
  end
  
// 10 unit clock cycle
  always 
    #5 clock = ~clock;

  always @(posedge clock)
     begin
       clock_cycle=clock_cycle+1;
     end


// display contents of pipeline latches at the end of each clock cycle
  always @(negedge clock) 
     begin
     $display("\n\nclock cycle = %d",clock_cycle," (time = %1.0t)",$time);
     $display("IF/ID registers\n\t IF/ID.PC+4 = %h, IF/ID.IR = %h \n", u_mipspipe_mp2.PC, u_mipspipe_mp2.IFIDIR); 
     $display("ID/EX registers\n\t ID/EX.rs = %d, ID/EX.rt = %d",u_mipspipe_mp2.IDEXrs,u_mipspipe_mp2.IDEXrt,"\n\t ID/EX.A = %h, ID/EX.B = %h",u_mipspipe_mp2.IDEXA,u_mipspipe_mp2.IDEXB);
     $display("\t ID/EX.op = %h\n",u_mipspipe_mp2.IDEXop);
     $display("EX/MEM registers\n\t EX/MEM.rs = %d, EX/MEM.rt = %d",u_mipspipe_mp2.IDEXrs,u_mipspipe_mp2.IDEXrt,"\n\t EX/MEM.ALUOut = %h, EX/MEM.ALUout = %h",u_mipspipe_mp2.EXMEMALUOut,u_mipspipe_mp2.EXMEMB);
     $display("\t EX/MEM.op = %h\n",u_mipspipe_mp2.EXMEMop);
     $display("MEM/WB registers\n\t MEM/WB.rd = %d, MEM/WB.rt = %d",u_mipspipe_mp2.MEMWBrd,u_mipspipe_mp2.MEMWBrt,"\n\t MEM/WB.value = %h",u_mipspipe_mp2.MEMWBValue);
     $display("\t EX/MEM.op = %h\n",u_mipspipe_mp2.MEMWBop);
     end
      
// log to a vcd (variable change dump) file
   initial
      begin
      $dumpfile("test_mipspipe.vcd");
      $dumpvars;
   end

endmodule

ee4363/mp2/test_mipspipe.vcd
$date
	Fri Dec 18 19:19:39 2020
$end
$version
	Icarus Verilog
$end
$timescale
	1s
$end
$scope module test_mipspipe $end
$var reg 1 ! clock $end
$var reg 4 " clock_cycle [3:0] $end
$scope module u_mipspipe_mp2 $end
$var wire 32 # Bin [31:0] $end
$var wire 1 $ STALL $end
$var wire 1 % bypassAfromALUinWB $end
$var wire 1 & bypassAfromLWinWB $end
$var wire 1 ' bypassAfromMEM $end
$var wire 1 ( bypassBfromALUinWB $end
$var wire 1 ) bypassBfromLWinWB $end
$var wire 1 * bypassBfromMEM $end
$var wire 1 + bypassIDEXAfromWB $end
$var wire 1 , bypassIDEXBfromWB $end
$var wire 1 ! clock $end
$var wire 5 - MEMWBrt [4:0] $end
$var wire 5 . MEMWBrd [4:0] $end
$var wire 6 / MEMWBop [5:0] $end
$var wire 5 0 IFIDrt [4:0] $end
$var wire 5 1 IFIDrs [4:0] $end
$var wire 6 2 IFIDop [5:0] $end
$var wire 5 3 IDEXrt [4:0] $end
$var wire 5 4 IDEXrs [4:0] $end
$var wire 6 5 IDEXop [5:0] $end
$var wire 5 6 EXMEMrd [4:0] $end
$var wire 6 7 EXMEMop [5:0] $end
$var wire 32 8 Ain [31:0] $end
$var reg 32 9 EXMEMALUOut [31:0] $end
$var reg 32 : EXMEMB [31:0] $end
$var reg 32 ; EXMEMIR [31:0] $end
$var reg 32 < IDEXA [31:0] $end
$var reg 32 = IDEXB [31:0] $end
$var reg 32 > IDEXIR [31:0] $end
$var reg 32 ? IFIDIR [31:0] $end
$var reg 32 @ MEMWBIR [31:0] $end
$var reg 32 A MEMWBValue [31:0] $end
$var reg 32 B PC [31:0] $end
$var reg 6 C i [5:0] $end
$var reg 11 D j [10:0] $end
$var reg 11 E k [10:0] $end
$upscope $end
$upscope $end
$enddefinitions $end
#0
$dumpvars
b10000000000 E
b10000000000 D
b100000 C
b0 B
bx A
b100000 @
b100000 ?
b100000 >
bx =
bx <
b100000 ;
bx :
bx 9
bx 8
b0 7
b0 6
b0 5
b0 4
b0 3
b0 2
b0 1
b0 0
b0 /
b0 .
b0 -
1,
1+
0*
0)
0(
0'
0&
0%
0$
bx #
b0 "
0!
$end
#5
0+
0,
b10 1
b1 0
b100 B
b10000010010100000100000 ?
b1 "
1!
#10
0!
#15
b10 8
b10 4
b1 3
b1 #
b101 1
b11 0
b100011 2
b10000010010100000100000 >
b1 =
b10 <
b1000 B
b10001100101000110000000000000100 ?
b10 "
1!
#20
0!
#25
1'
b11 8
b101 6
b101 4
b11 3
b100011 5
b11 #
b111 0
b101011 2
b1 :
b10000010010100000100000 ;
b11 9
b10001100101000110000000000000100 >
b11 =
b101 <
b1100 B
b10101100101001110000000000000101 ?
b11 "
1!
#30
0!
#35
0'
b101 .
b1 -
b0 6
b100011 7
b101 8
b111 3
b101011 5
b111 #
b11 1
b0 0
b0 2
b10000010010100000100000 @
b11 A
b11 :
b10001100101000110000000000000100 ;
b111 9
b10101100101001110000000000000101 >
b111 =
b10000 B
b11000000010000000100000 ?
b100 "
1!
#40
0!
#45
1&
b11111111111111111111111111111111 8
b0 .
b11 -
b100011 /
b101011 7
b11 4
b0 3
b0 5
b0 #
b1000 1
b1001 0
b10001100101000110000000000000100 @
b11111111111111111111111111111111 A
b111 :
b10101100101001110000000000000101 ;
b1010 9
b11000000010000000100000 >
b0 =
b11 <
b10100 B
b1000010010011000000100000 ?
b101 "
1!
#50
0!
#55
b1000 8
0&
b111 -
b101011 /
b100 6
b0 7
b1000 4
b1001 3
b1001 #
b0 1
b110 0
b101011 2
b10101100101001110000000000000101 @
b0 :
b11000000010000000100000 ;
b11111111111111111111111111111111 9
b1000010010011000000100000 >
b1001 =
b1000 <
b11000 B
b10101100000001100000000000001100 ?
b110 "
1!
#60
0!
#65
b0 8
b100 .
b0 -
b0 /
b110 6
b0 4
b110 3
b101011 5
b110 #
b110 1
b0 0
b0 2
b11000000010000000100000 @
b1001 :
b1000010010011000000100000 ;
b10001 9
b10101100000001100000000000001100 >
b110 =
b0 <
b11100 B
b110000000101000000100000 ?
b111 "
1!
#70
0!
#75
b110 8
b110 .
b1001 -
b0 6
b101011 7
b110 4
b0 3
b0 5
b0 #
b0 1
b1011 0
b100011 2
b1000010010011000000100000 @
b10001 A
b110 :
b10101100000001100000000000001100 ;
b1100 9
b110000000101000000100000 >
b0 =
b110 <
b100000 B
b10001100000010110000000000010000 ?
b1000 "
1!
#80
0!
#85
0$
b0 8
b0 .
b110 -
b101011 /
b1010 6
b0 7
b0 4
b1011 3
b100011 5
b1011 #
b0 0
b0 2
b10101100000001100000000000001100 @
b0 :
b110000000101000000100000 ;
b110 9
b10001100000010110000000000010000 >
b1011 =
b0 <
b100100 B
b100000 ?
b1001 "
1!
#90
0!
#95
b1010 .
b0 -
b0 /
b0 6
b100011 7
b0 3
b0 5
b0 #
b1 1
b1011 0
b110000000101000000100000 @
b110 A
b1011 :
b10001100000010110000000000010000 ;
b10000 9
b100000 >
b0 =
b101000 B
b1010110110000000100000 ?
b1010 "
1!
#100
0!
#105
b1 8
b0 .
b1011 -
b100011 /
b0 7
b1 4
b1011 3
b1011 #
b0 1
b0 0
b10001100000010110000000000010000 @
b11111111111111111111111111111110 A
b0 :
b100000 ;
b0 9
b1010110110000000100000 >
b1011 =
b1 <
b101100 B
b100000 ?
b1011 "
1!
#110
0!
#115
1+
1,
b0 8
b0 -
b0 /
b1100 6
b0 4
b0 3
b0 #
b100000 @
b0 A
b1011 :
b1010110110000000100000 ;
b1100 9
b100000 >
b0 =
b0 <
b110000 B
b1100 "
1!
#120
0!
#125
0+
0,
b1100 .
b1011 -
b0 6
b1010110110000000100000 @
b1100 A
b0 :
b100000 ;
b0 9
b110100 B
b1101 "
1!
#130
0!
#135
1+
1,
b0 .
b0 -
b100000 @
b0 A
b111000 B
b1110 "
1!
#140
0!
#145
b111100 B
b1111 "
1!
#150
0!
#155
b1000000 B
b0 "
1!
